setup.py
ekarfan_pypi_test.egg-info/PKG-INFO
ekarfan_pypi_test.egg-info/SOURCES.txt
ekarfan_pypi_test.egg-info/dependency_links.txt
ekarfan_pypi_test.egg-info/not-zip-safe
ekarfan_pypi_test.egg-info/top_level.txt
package_name/__init__.py
package_name/python_code.py